Metadata-Version: 2.1
Name: bg-probability-distributions
Version: 1.0
Summary: Binomial and Gaussian distributions
Home-page: UNKNOWN
Author: Ifeoluwa Oderinde
Author-email: oderindeife@gmail.com
License: UNKNOWN
Platform: UNKNOWN
